model_profiler/__init__.py
model_profiler/draw_graph_bytorchview.py
model_profiler/estimatetime.py
model_profiler/export2excel.py
model_profiler/profiler.py
torch_model_profiler-0.1.1.dist-info/METADATA
torch_model_profiler-0.1.1.dist-info/WHEEL
torch_model_profiler-0.1.1.dist-info/top_level.txt
torch_model_profiler-0.1.1.dist-info/RECORD
