Metadata-Version: 2.4
Name: torch-model-profiler
Version: 0.1.1
Summary: A PyTorch model profiling tool for FLOPs, memory, and visualization.
Author-email: "Chih-Sheng (Tommy) Huang" <chih.sheng.huang821@gmail.com>
License: MIT
Project-URL: Homepage, https://github.com/TommyHuang821/model_profiler
Project-URL: Repository, https://github.com/TommyHuang821/model_profiler
Project-URL: Issues, https://github.com/TommyHuang821/model_profiler/issues
Classifier: Programming Language :: Python :: 3
Classifier: License :: OSI Approved :: MIT License
Classifier: Operating System :: OS Independent
Requires-Python: >=3.7
Requires-Dist: torch>=1.9
Requires-Dist: torchvision
Requires-Dist: prettytable
Requires-Dist: openpyxl
Requires-Dist: graphviz
Requires-Dist: torchview
